core_utils_base/__init__.py
core_utils_base/enum_utils.py
core_utils_base/formatting_utils.py
core_utils_base/hash_utils.py
core_utils_base/py.typed
core_utils_base/pydantic_utils.py
core_utils_base/python_utils.py
core_utils_base/toml_utils.py
core_utils_base/url_utils.py
turintech_base_utils-1.0.0a3.dist-info/METADATA
turintech_base_utils-1.0.0a3.dist-info/WHEEL
turintech_base_utils-1.0.0a3.dist-info/licenses/LICENSE
turintech_base_utils-1.0.0a3.dist-info/RECORD
