Metadata-Version: 2.4
Name: turintech_base_utils
Version: 1.0.0a3
Summary: Base utilities with no external core dependencies
License-Expression: LicenseRef-Turing-Intelligence-Technology-EULA
License-File: LICENSE
Classifier: Development Status :: 5 - Production/Stable
Classifier: License :: Other/Proprietary License
Requires-Python: <3.14,>=3.11
Requires-Dist: packaging<25.0,>=23.0
Requires-Dist: pydantic<3.0.0,>=2
Requires-Dist: toml<1.0.0
